<Talk>
  <Id>How-we-created-DotNetRu-App</Id>
  <SpeakerIds>
    <SpeakerId>Pavel-Fedotovsky</SpeakerId>
  </SpeakerIds>
  <Title>Как мы разрабатывали приложение для DotNetRu на Xamarin.Forms</Title>
  <Description>Про Xamarin.Forms наверное уже слышал каждый — после покупки Xamarin Microsoft’ом платформа довольно активно развивается. В этом докладе будет анонс приложения для сообществ DotNetRu написанного на Xamarin.Forms. Поговорим про то, как мы его разрабатывали, с какими сложностями столкнулись и как их решали. Мы рассмотрим весь цикл создания, от настройки окружения до публикации в магазины. Обязательно затронем такие темы как:

- какие есть возможности отладки приложения;
- как сделать общий код для разных платформ;
- локализация;
- мониторинг.

Приложение отрытое и разрабатывается добровольцами. После доклада у каждого из вас будет достаточно информации, чтобы присоединиться к миру Open Source и вместе с сообществом создавать DotNetRu App.</Description>
  <SlidesUrl>https://speakerdeck.com/dotnetru/paviel-fiedotovskii-kak-my-razrabatyvali-prilozhieniie-dlia-dotnetru-na-xamarin-dot-forms</SlidesUrl>
  <VideoUrl>https://www.youtube.com/watch?v=qAiQyTpXFxw</VideoUrl>
</Talk>
