<Talk>
  <Id>Practical-Aspects-Migrating-To-Microservices</Id>
  <SpeakerIds>
    <SpeakerId>Andrey-Schilling</SpeakerId>
  </SpeakerIds>
  <Title>Практические аспекты перехода на микросервисы</Title>
  <Description>Хайп вокруг микросервисов не утихает уже который год и сегодня они стали мейнстримом. К чему нужно быть готовым сразу, а что отложить на потом, ступая на этот путь? Мы поговорим про практические и философские аспекты миграции на микросервисы в enterprise-разработках и о том, о чем не всегда пишут в интернете.</Description>
  <VideoUrl>https://www.youtube.com/watch?v=8l9QxJEBi_k</VideoUrl>
  <SlidesUrl>https://vk.com/doc-161778786_469646719</SlidesUrl>
</Talk>
