<Talk>
  <Id>Why-Request-for-EF6-so-Slow</Id>
  <SpeakerIds>
    <SpeakerId>Alex-Kapustyanenko</SpeakerId>
  </SpeakerIds>
  <Title>Почему же мой запрос на Entity Framework 6 так тормозит? Часть 9000</Title>
  <Description>Алексей расскажет о хитростях кеширования в Entity Framework 6 и о том, как простые на первый взгляд LINQ-выражения могут замедлить ваши запросы на несколько порядков.</Description>
  <SlidesUrl>https://speakerdeck.com/dotnetru/alieksiei-kapustianienko-pochiemu-zhie-moi-zapros-na-entity-framework-6-tormozit-chast-9000</SlidesUrl>
  <VideoUrl>https://www.youtube.com/watch?v=IQjFIvkuFhM</VideoUrl>
</Talk>
